bq_etl/__init__.py
bq_etl-0.0.2.dist-info/LICENSE
bq_etl-0.0.2.dist-info/METADATA
bq_etl-0.0.2.dist-info/WHEEL
bq_etl-0.0.2.dist-info/top_level.txt
bq_etl-0.0.2.dist-info/RECORD
