Metadata-Version: 2.1
Name: bq-etl
Version: 0.0.2
Summary: Simple BigQuery ETL
Home-page: https://github.com/grisha/bq_etl
Author: Gregory Trubetskoy
Author-email: grisha@grisha.org
License: UNKNOWN
Platform: UNKNOWN
Classifier: Programming Language :: Python :: 3
Classifier: License :: OSI Approved :: Apache Software License
Classifier: Operating System :: OS Independent
Requires-Python: >=3.0
Requires-Dist: google-cloud-bigquery (>=1.22.0)
Requires-Dist: google-cloud-storage (>=1.23.0)
